taseq/__init__.py
taseq/adapter.py
taseq/default.py
taseq/draw.py
taseq/extractref.py
taseq/filter.py
taseq/genotype.py
taseq/hapcall.py
taseq/mapping.py
taseq/mergevcf.py
taseq/params.py
taseq/refindex.py
taseq/trimmomatic.py
taseq/utils.py
taseq-1.1.1.dist-info/LICENSE
taseq-1.1.1.dist-info/METADATA
taseq-1.1.1.dist-info/WHEEL
taseq-1.1.1.dist-info/entry_points.txt
taseq-1.1.1.dist-info/top_level.txt
taseq-1.1.1.dist-info/RECORD
