Metadata-Version: 2.1
Name: taseq
Version: 1.1.1
Summary: Downstream analysis for targetted amplicon sequencing.
Home-page: https://github.com/KChigira/taseq/
Author: Koki Chigira
Author-email: kyoujin2009kutar@gmail.com
License: MIT
Platform: UNKNOWN
Requires-Dist: pandas
Requires-Dist: matplotlib
